openjsoncanvas.py
openjsoncanvas-3.0.0.dist-info/LICENSE
openjsoncanvas-3.0.0.dist-info/WHEEL
openjsoncanvas-3.0.0.dist-info/METADATA
openjsoncanvas-3.0.0.dist-info/RECORD
