Metadata-Version: 2.1
Name: openjsoncanvas
Version: 3.0.0
Summary: A python implementation of the JsonCanvas format: https://github.com/obsidianmd/jsoncanvas/blob/main/spec/1.0.md
Author: Alyce Osbourne
Classifier: License :: OSI Approved :: MIT License
Requires-Dist: pydantic
Project-URL: Home, https://github.com/AlyceOsbourne/openjsoncanvas
